xpi2pkgbuild/__init__.py
xpi2pkgbuild/xpi2pkgbuild.py
xpi2pkgbuild-1.1.0.dist-info/entry_points.txt
xpi2pkgbuild-1.1.0.dist-info/LICENSE
xpi2pkgbuild-1.1.0.dist-info/WHEEL
xpi2pkgbuild-1.1.0.dist-info/METADATA
xpi2pkgbuild-1.1.0.dist-info/RECORD
