Metadata-Version: 2.1
Name: xpi2pkgbuild
Version: 1.1.0
Summary: Mozilla XPI based PKGBUILD generator using mozilla addon API.
Author-email: Rafael Silva <perigoso@riseup.net>
Requires-Python: >=3.7
Classifier: License :: OSI Approved :: MIT License
Classifier: Development Status :: 5 - Production/Stable
Classifier: Intended Audience :: Developers
Classifier: Programming Language :: Python :: 3
Classifier: Programming Language :: Python :: 3 :: Only
Project-URL: Home, https://github.com/perigoso/xpi2pkgbuild
